mmcli/helper.py
mmcli/mmadmin.py
mmcli/mmcli.py
mmcli/mmclient.py
mmdok_cli-1.15.dist-info/LICENSE
mmdok_cli-1.15.dist-info/METADATA
mmdok_cli-1.15.dist-info/PKG-INFO.bak
mmdok_cli-1.15.dist-info/WHEEL
mmdok_cli-1.15.dist-info/entry_points.txt
mmdok_cli-1.15.dist-info/top_level.txt
mmdok_cli-1.15.dist-info/RECORD
