Metadata-Version: 2.1
Name: mmdok-cli
Version: 1.15
Summary: Cli client for TinyDS
Home-page: https://github.com/emagnca/mmcli
Author: emagnca
Author-email: ehsmaga@yahoo.se
License: BSD 2-clause
Classifier: Development Status :: 1 - Planning
Classifier: License :: OSI Approved :: BSD License
Classifier: Programming Language :: Python :: 3 :: Only
License-File: LICENSE
Requires-Dist: cmd2 ==1.5.0
Requires-Dist: requests ==2.25.0
Requires-Dist: urllib3 ==1.26.2
